PydoNovosoft/__init__.py
PydoNovosoft/slack.py
PydoNovosoft/utils.py
PydoNovosoft/classes/PeriodicPositionProto_pb2.py
PydoNovosoft/classes/__init__.py
PydoNovosoft/classes/mzone.py
PydoNovosoft/classes/scope.py
PydoNovosoft/scope/CanVehicleInfoProto_pb2.py
PydoNovosoft/scope/CellocatorModularType11Proto_pb2.py
PydoNovosoft/scope/ConsumptionProto_pb2.py
PydoNovosoft/scope/EventHeaderProto_pb2.py
PydoNovosoft/scope/FuelLevelProto_pb2.py
PydoNovosoft/scope/PeriodicPositionProto_pb2.py
PydoNovosoft/scope/TripSpeedSourceProto_pb2.py
PydoNovosoft/scope/__init__.py
PydoNovosoft/scope/mprofiler.py
PydoNovosoft/scope/mzone.py
PydoNovosoft/scope/mzone4.py
PydoNovosoft/scope/scope.py
PydoNovosoft/sugarcrm/__init__.py
PydoNovosoft/sugarcrm/sugarcrm.py
PydoNovosoft/tests/__init__.py
PydoNovosoft/tests/test.py
PydoNovosoft/tests/test_mzone4.py
PydoNovosoft/tests/test_scope.py
PydoNovosoft/tests/test_slack.py
PydoNovosoft/tests/test_utils.py
PydoNovosoft-1.3.1.dist-info/LICENSE
PydoNovosoft-1.3.1.dist-info/METADATA
PydoNovosoft-1.3.1.dist-info/WHEEL
PydoNovosoft-1.3.1.dist-info/top_level.txt
PydoNovosoft-1.3.1.dist-info/RECORD
