Metadata-Version: 2.1
Name: PydoNovosoft
Version: 1.3.1
Summary: Some Python's utilities for other projects
Home-page: https://github.com/donovosoft/PydoNovosoft
Author: Mauricio Barrera
Author-email: mauricio.barrerag@gmail.com
License: UNKNOWN
Platform: UNKNOWN
Classifier: Programming Language :: Python :: 2.7
Classifier: License :: OSI Approved :: MIT License
Classifier: Operating System :: OS Independent
Requires-Dist: protobuf
Requires-Dist: pytz
